{
  "hash": "8e14320d295e15540b7b747f84270517",
  "result": {
    "markdown": "---\ntitle: \"Module 4\"\nsubtitle: \"Data organization in spreadsheets\"\neditor: source\nparams:\n    week: 4\nexecute: \n  echo: false\n  warning: false\n---\n\n\n## {{< fa bullseye >}} Learning Objectives\n\n\n::: {.cell}\n\n:::\n\n\n1. Learners can apply 12 principles for data organisation in spreadsheets to the layout of a provided dataset.\n2. Learners can discuss the difference between data in an unprocessed structure and in a processed structure.\n\n## {{< fa display >}} Slides\n\n- In preparation\n\n## {{< fa book >}} Readings\n\n3. Read [Data Organization in Spreadsheets](https://www.tandfonline.com/doi/full/10.1080/00031305.2017.1375989)\n\n## {{< fa code >}} Assignments\n\n- In preparation\n\n",
    "supporting": [
      "md-04_files"
    ],
    "filters": [
      "rmarkdown/pagebreak.lua"
    ],
    "includes": {},
    "engineDependencies": {},
    "preserve": {},
    "postProcess": true
  }
}