{
  "hash": "830e242357d38cd71fa801782ea9b1c7",
  "result": {
    "engine": "knitr",
    "markdown": "---\ntitle: \"Module 12\"\nsubtitle: \"{{< var md-12.title >}}\"\neditor: source\nparams:\n    module: 12\nexecute: \n  echo: false\n  warning: false\n---\n\n\n## {{< fa bullseye >}} Learning Objectives\n\n\n::: {.cell}\n\n:::\n\n::: {.cell}\n\n:::\n\n::: {.cell}\n1. \n:::\n\n\n## {{< fa display >}} Slides\n\n- In preparation\n\n## {{< fa code >}} Assignments\n\n- In preparation\n",
    "supporting": [],
    "filters": [
      "rmarkdown/pagebreak.lua"
    ],
    "includes": {},
    "engineDependencies": {},
    "preserve": {},
    "postProcess": true
  }
}